kikan/__init__.py
kikan/engine.py
kikan/entity.py
kikan/errors.py
kikan/events.py
kikan/main.py
kikan/math.py
kikan/physics.py
kikan/screen.py
kikan/signals.py
kikan/states.py
kikan/utils.py
kikan/world.py
kikan-0.0.3.dist-info/METADATA
kikan-0.0.3.dist-info/WHEEL
kikan-0.0.3.dist-info/licenses/LICENSE
kikan-0.0.3.dist-info/RECORD
