Metadata-Version: 2.3
Name: kikan
Version: 0.0.3
Summary: TUI-based game engine
Project-URL: Bug Tracker, https://github.com/idkarn/kikan/issues
Project-URL: Homepage, https://github.com/idkarn/kikan
Author-email: Kir Ivanov <asagiri@duck.com>
License-File: LICENSE
Classifier: License :: OSI Approved :: MIT License
Classifier: Operating System :: OS Independent
Classifier: Programming Language :: Python :: 3
Requires-Python: >=3.9
Requires-Dist: blessed
